setup.py
vcclick/__init__.py
vcclick/main.py
vcclick.egg-info/PKG-INFO
vcclick.egg-info/SOURCES.txt
vcclick.egg-info/dependency_links.txt
vcclick.egg-info/requires.txt
vcclick.egg-info/top_level.txt